fast_dataindex/helpers.cpython-37m-aarch64-linux-gnu.so
fast_dataindex-0.1.2.dist-info/METADATA
fast_dataindex-0.1.2.dist-info/WHEEL
fast_dataindex-0.1.2.dist-info/top_level.txt
fast_dataindex-0.1.2.dist-info/RECORD
