Metadata-Version: 2.1
Name: fast-dataindex
Version: 0.1.2
Summary: Data tool helpers for PaddleNLP pre-training.
Home-page: https://github.com/PaddlePaddle/PaddleNLP/blob/develop/model_zoo/ernie-1.0/data_tools
Author: PaddleNLP Team
Author-email: paddlenlp@baidu.com
License: Apache 2.0
Classifier: Programming Language :: C++
Classifier: Programming Language :: Python :: 3
Classifier: Programming Language :: Python :: 3.6
Classifier: Programming Language :: Python :: 3.7
Classifier: Programming Language :: Python :: 3.8
Classifier: Programming Language :: Python :: 3.9
Classifier: Programming Language :: Python :: 3.10
Classifier: License :: OSI Approved :: Apache Software License
Classifier: Operating System :: OS Independent
Requires-Python: >=3.6
Requires-Dist: numpy <=1.26.4
Requires-Dist: pybind11
